djaizz/__init__.py
djaizz/urls.py
djaizz/client/__init__.py
djaizz/data/admin.py
djaizz/data/apps.py
djaizz/data/urls.py
djaizz/data/api/__init__.py
djaizz/data/api/gql/__init__.py
djaizz/data/api/json/__init__.py
djaizz/data/api/rest/__init__.py
djaizz/data/migrations/0001_DataSchema_DataSet.py
djaizz/data/migrations/0002_InDBJSONDataSet.py
djaizz/data/migrations/0003_Django4.py
djaizz/data/migrations/__init__.py
djaizz/data/models/__init__.py
djaizz/data/models/audio.py
djaizz/data/models/base.py
djaizz/data/models/csv.py
djaizz/data/models/hdf.py
djaizz/data/models/image.py
djaizz/data/models/json.py
djaizz/data/models/live_api.py
djaizz/data/models/numpy.py
djaizz/data/models/orc.py
djaizz/data/models/pandas.py
djaizz/data/models/parquet.py
djaizz/data/models/text.py
djaizz/data/models/tfrecord.py
djaizz/data/models/video.py
djaizz/data/models/public/__init__.py
djaizz/data/models/public/gov.py
djaizz/data/models/public/hugging_face.py
djaizz/data/models/public/intl_dev.py
djaizz/data/models/public/kaggle.py
djaizz/data/models/public/tf.py
djaizz/data/models/public/torch.py
djaizz/data/models/public/weather.py
djaizz/model/admin.py
djaizz/model/apps.py
djaizz/model/urls.py
djaizz/model/views.py
djaizz/model/api/__init__.py
djaizz/model/api/gql/__init__.py
djaizz/model/api/json/__init__.py
djaizz/model/api/rest/__init__.py
djaizz/model/migrations/0001_AIModel.py
djaizz/model/migrations/0002_PreTrainedKerasImageNetClassifier.py
djaizz/model/migrations/0003_PreTrainedHuggingFaceTransformers.py
djaizz/model/migrations/0004_CloudAIService.py
djaizz/model/migrations/0005_GoogleTranslate.py
djaizz/model/migrations/0006_Django4.py
djaizz/model/migrations/__init__.py
djaizz/model/models/__init__.py
djaizz/model/models/base.py
djaizz/model/models/cloud_ai_svc/__init__.py
djaizz/model/models/cloud_ai_svc/base.py
djaizz/model/models/cloud_ai_svc/amazon/__init__.py
djaizz/model/models/cloud_ai_svc/google/__init__.py
djaizz/model/models/cloud_ai_svc/google/translation.py
Djaizz-23.6.21.1.dist-info/LICENSE
Djaizz-23.6.21.1.dist-info/METADATA
Djaizz-23.6.21.1.dist-info/WHEEL
Djaizz-23.6.21.1.dist-info/entry_points.txt
Djaizz-23.6.21.1.dist-info/top_level.txt
Djaizz-23.6.21.1.dist-info/zip-safe
Djaizz-23.6.21.1.dist-info/RECORD
